{
  "timestamp": "2026-02-28T04:58:34.459712",
  "strategies": [
    {
      "strategy": "TrendFollowing",
      "type": "trend",
      "allocation": 0.15,
      "total_signals": 22,
      "buy_signals": 3,
      "sell_signals": 19,
      "signals": [
        {
          "symbol": "BTC/USDT",
          "side": "sell",
          "score": 0.7390097607040037,
          "confidence": 0.791207808563203,
          "metadata": {
            "ma_fast": 66717.12999999999,
            "ma_slow": 67352.37,
            "adx": 36.95048803520019
          }
        },
        {
          "symbol": "ETH/USDT",
          "side": "sell",
          "score": 0.9658620135232452,
          "confidence": 0.9726896108185963,
          "metadata": {
            "ma_fast": 1988.0880000000002,
            "ma_slow": 2016.9601666666667,
            "adx": 48.29310067616226
          }
        },
        {
          "symbol": "SOL/USDT",
          "side": "sell",
          "score": 0.9260192991502388,
          "confidence": 0.9408154393201911,
          "metadata": {
            "ma_fast": 84.7825,
            "ma_slow": 86.08933333333333,
            "adx": 46.300964957511944
          }
        },
        {
          "symbol": "BNB/USDT",
          "side": "sell",
          "score": 1.0,
          "confidence": 1.0,
          "metadata": {
            "ma_fast": 620.635,
            "ma_slow": 622.4833333333333,
            "adx": 51.64739479816397
          }
        },
        {
          "symbol": "ADA/USDT",
          "side": "sell",
          "score": 0.5684090378765417,
          "confidence": 0.6547272303012335,
          "metadata": {
            "ma_fast": 0.28555,
            "ma_slow": 0.28866,
            "adx": 28.420451893827085
          }
        }
      ]
    },
    {
      "strategy": "MeanReversion",
      "type": "mean_reversion",
      "allocation": 0.35,
      "total_signals": 9,
      "buy_signals": 9,
      "sell_signals": 0,
      "signals": [
        {
          "symbol": "ETH/USDT",
          "side": "buy",
          "score": 0.5786045414546089,
          "confidence": 0.620744087309148,
          "metadata": {
            "rsi": 11.799072839270949,
            "deviation": -0.033594086378470285,
            "bb_lower": 1894.9917997044222
          }
        },
        {
          "symbol": "SOL/USDT",
          "side": "buy",
          "score": 0.5127892813641937,
          "confidence": 0.5615103532277743,
          "metadata": {
            "rsi": 13.641900121802578,
            "deviation": -0.03789107421932599,
            "bb_lower": 79.9479930039621
          }
        },
        {
          "symbol": "ADA/USDT",
          "side": "buy",
          "score": 0.4495647721454148,
          "confidence": 0.5046082949308733,
          "metadata": {
            "rsi": 15.412186379928386,
            "deviation": -0.03484503589564004,
            "bb_lower": 0.2736747714703443
          }
        },
        {
          "symbol": "POL/USDT",
          "side": "buy",
          "score": 0.027165932452278798,
          "confidence": 0.12444933920705092,
          "metadata": {
            "rsi": 27.239353891336194,
            "deviation": -0.029848408219165855,
            "bb_lower": 0.10649148020399411
          }
        },
        {
          "symbol": "NEAR/USDT",
          "side": "buy",
          "score": 0.3021346469622352,
          "confidence": 0.3719211822660117,
          "metadata": {
            "rsi": 19.540229885057414,
            "deviation": -0.029464285714285835,
            "bb_lower": 1.0858116671178162
          }
        }
      ]
    },
    {
      "strategy": "Alpha6Factor",
      "type": "alpha_6factor",
      "allocation": 0.5,
      "total_signals": 27,
      "buy_signals": 6,
      "sell_signals": 21,
      "signals": [
        {
          "symbol": "BTC/USDT",
          "side": "sell",
          "score": 1.1259469653781877,
          "confidence": 1.0,
          "metadata": {
            "raw_factors": {
              "f1_mom_5d": -0.029686384887362898,
              "f2_mom_20d": -0.07130269064345682,
              "f3_vol_adj_ret": -13.23847302471365,
              "f4_volume_expansion": 0.21312621001677168,
              "f5_rsi_trend_confirm": -0.5061760726288682,
              "f6_sentiment": 0.0839
            },
            "z_factors": {
              "f1_mom_5d": -0.296863848873629,
              "f2_mom_20d": -0.35651345321728406,
              "f3_vol_adj_ret": -6.619236512356825,
              "f4_volume_expansion": 0.42625242003354336,
              "f5_rsi_trend_confirm": -0.5061760726288682,
              "f6_sentiment": 0.0839
            },
            "final_score": -1.1259469653781877
          }
        },
        {
          "symbol": "ETH/USDT",
          "side": "sell",
          "score": 1.0223691017594,
          "confidence": 1.0,
          "metadata": {
            "raw_factors": {
              "f1_mom_5d": -0.010251390892231656,
              "f2_mom_20d": -0.07123002924612676,
              "f3_vol_adj_ret": -10.445047498159475,
              "f4_volume_expansion": -0.0831271167308224,
              "f5_rsi_trend_confirm": -0.7640185432145811,
              "f6_sentiment": 0.0331
            },
            "z_factors": {
              "f1_mom_5d": -0.10251390892231656,
              "f2_mom_20d": -0.3561501462306338,
              "f3_vol_adj_ret": -5.222523749079738,
              "f4_volume_expansion": -0.1662542334616448,
              "f5_rsi_trend_confirm": -0.7640185432145811,
              "f6_sentiment": 0.0331
            },
            "final_score": -1.0223691017594
          }
        },
        {
          "symbol": "SOL/USDT",
          "side": "sell",
          "score": 1.2187959949843075,
          "confidence": 1.0,
          "metadata": {
            "raw_factors": {
              "f1_mom_5d": -0.01746567092266927,
              "f2_mom_20d": -0.0937673591823132,
              "f3_vol_adj_ret": -12.51747767699662,
              "f4_volume_expansion": -0.0758772140435785,
              "f5_rsi_trend_confirm": -0.7271619975639484,
              "f6_sentiment": -0.0316
            },
            "z_factors": {
              "f1_mom_5d": -0.17465670922669269,
              "f2_mom_20d": -0.46883679591156596,
              "f3_vol_adj_ret": -6.25873883849831,
              "f4_volume_expansion": -0.151754428087157,
              "f5_rsi_trend_confirm": -0.7271619975639484,
              "f6_sentiment": -0.0316
            },
            "final_score": -1.2187959949843075
          }
        },
        {
          "symbol": "BNB/USDT",
          "side": "sell",
          "score": 0.5732101215947566,
          "confidence": 0.5732101215947566,
          "metadata": {
            "raw_factors": {
              "f1_mom_5d": -0.0027805037618579193,
              "f2_mom_20d": -0.03344958782498401,
              "f3_vol_adj_ret": -6.035883429775734,
              "f4_volume_expansion": -0.026296312056200644,
              "f5_rsi_trend_confirm": -0.6443148688046628,
              "f6_sentiment": 0.2
            },
            "z_factors": {
              "f1_mom_5d": -0.027805037618579193,
              "f2_mom_20d": -0.16724793912492003,
              "f3_vol_adj_ret": -3.017941714887867,
              "f4_volume_expansion": -0.05259262411240129,
              "f5_rsi_trend_confirm": -0.6443148688046628,
              "f6_sentiment": 0.2
            },
            "final_score": -0.5732101215947566
          }
        },
        {
          "symbol": "ADA/USDT",
          "side": "sell",
          "score": 0.8423836888408011,
          "confidence": 0.8423836888408011,
          "metadata": {
            "raw_factors": {
              "f1_mom_5d": 0.024154589371980697,
              "f2_mom_20d": -0.0676589986468199,
              "f3_vol_adj_ret": -8.165539838713126,
              "f4_volume_expansion": -0.20434298608849322,
              "f5_rsi_trend_confirm": -0.6917562724014323,
              "f6_sentiment": -0.1104
            },
            "z_factors": {
              "f1_mom_5d": 0.24154589371980695,
              "f2_mom_20d": -0.3382949932340995,
              "f3_vol_adj_ret": -4.082769919356563,
              "f4_volume_expansion": -0.40868597217698643,
              "f5_rsi_trend_confirm": -0.6917562724014323,
              "f6_sentiment": -0.1104
            },
            "final_score": -0.8423836888408011
          }
        }
      ]
    }
  ]
}