{
  "ts": "2026-02-28T19:00:35.783595Z",
  "run_id": "20260301_03",
  "window_start_ts": 1772301600,
  "window_end_ts": 1772305200,
  "symbols": [
    {
      "symbol": "BTC/USDT",
      "bid": 65884.5,
      "ask": 65884.6,
      "mid": 65884.55,
      "spread_bps": 0.015178065268081934,
      "selected": false
    },
    {
      "symbol": "ETH/USDT",
      "bid": 1935.2,
      "ask": 1935.21,
      "mid": 1935.205,
      "spread_bps": 0.05167411204493015,
      "selected": false
    },
    {
      "symbol": "SOL/USDT",
      "bid": 82.33,
      "ask": 82.34,
      "mid": 82.33500000000001,
      "spread_bps": 1.2145503127473267,
      "selected": false
    },
    {
      "symbol": "BNB/USDT",
      "bid": 612.0,
      "ask": 612.1,
      "mid": 612.05,
      "spread_bps": 1.6338534433465033,
      "selected": false
    },
    {
      "symbol": "ADA/USDT",
      "bid": 0.2738,
      "ask": 0.2739,
      "mid": 0.27385,
      "spread_bps": 3.6516341062621507,
      "selected": false
    },
    {
      "symbol": "DOT/USDT",
      "bid": 1.588,
      "ask": 1.589,
      "mid": 1.5885,
      "spread_bps": 6.295247088447527,
      "selected": true
    },
    {
      "symbol": "AVAX/USDT",
      "bid": 8.895,
      "ask": 8.896,
      "mid": 8.8955,
      "spread_bps": 1.1241639030984454,
      "selected": false
    },
    {
      "symbol": "POL/USDT",
      "bid": 0.10548,
      "ask": 0.10552,
      "mid": 0.10550000000000001,
      "spread_bps": 3.7914691943126417,
      "selected": false
    },
    {
      "symbol": "ATOM/USDT",
      "bid": 1.831,
      "ask": 1.832,
      "mid": 1.8315000000000001,
      "spread_bps": 5.46000546000607,
      "selected": false
    },
    {
      "symbol": "NEAR/USDT",
      "bid": 1.105,
      "ask": 1.106,
      "mid": 1.1055000000000001,
      "spread_bps": 9.045680687472744,
      "selected": true
    },
    {
      "symbol": "LINK/USDT",
      "bid": 8.616,
      "ask": 8.617,
      "mid": 8.6165,
      "spread_bps": 1.160564034122001,
      "selected": false
    },
    {
      "symbol": "UNI/USDT",
      "bid": 3.755,
      "ask": 3.756,
      "mid": 3.7554999999999996,
      "spread_bps": 2.6627612834506458,
      "selected": true
    },
    {
      "symbol": "AAVE/USDT",
      "bid": 110.1,
      "ask": 110.11,
      "mid": 110.10499999999999,
      "spread_bps": 0.908223968030981,
      "selected": false
    },
    {
      "symbol": "LTC/USDT",
      "bid": 53.84,
      "ask": 53.85,
      "mid": 53.845,
      "spread_bps": 1.857182653913643,
      "selected": false
    },
    {
      "symbol": "BCH/USDT",
      "bid": 447.3,
      "ask": 447.4,
      "mid": 447.35,
      "spread_bps": 2.2353861629588887,
      "selected": false
    },
    {
      "symbol": "ETC/USDT",
      "bid": 8.452,
      "ask": 8.454,
      "mid": 8.453,
      "spread_bps": 2.3660238968421483,
      "selected": false
    },
    {
      "symbol": "XRP/USDT",
      "bid": 1.3425,
      "ask": 1.3426,
      "mid": 1.3425500000000001,
      "spread_bps": 0.744851215969528,
      "selected": false
    },
    {
      "symbol": "DOGE/USDT",
      "bid": 0.09214,
      "ask": 0.09215,
      "mid": 0.092145,
      "spread_bps": 1.085246079548117,
      "selected": false
    },
    {
      "symbol": "TRX/USDT",
      "bid": 0.28216,
      "ask": 0.28217,
      "mid": 0.282165,
      "spread_bps": 0.35440256587296404,
      "selected": true
    },
    {
      "symbol": "SUI/USDT",
      "bid": 0.878,
      "ask": 0.8781,
      "mid": 0.87805,
      "spread_bps": 1.138887307100837,
      "selected": false
    },
    {
      "symbol": "HYPE/USDT",
      "bid": 29.348,
      "ask": 29.35,
      "mid": 29.349,
      "spread_bps": 0.6814542233133818,
      "selected": false
    },
    {
      "symbol": "PAXG/USDT",
      "bid": 5422.9,
      "ask": 5424.3,
      "mid": 5423.6,
      "spread_bps": 2.5813113061445265,
      "selected": true
    },
    {
      "symbol": "PI/USDT",
      "bid": 0.169,
      "ask": 0.1691,
      "mid": 0.16905,
      "spread_bps": 5.915409642117065,
      "selected": false
    },
    {
      "symbol": "OKB/USDT",
      "bid": 75.88,
      "ask": 75.91,
      "mid": 75.895,
      "spread_bps": 3.9528295671653124,
      "selected": false
    },
    {
      "symbol": "FIL/USDT",
      "bid": 0.9694,
      "ask": 0.9696,
      "mid": 0.9695,
      "spread_bps": 2.0629190304278286,
      "selected": false
    },
    {
      "symbol": "CC/USDT",
      "bid": 0.16863,
      "ask": 0.16865,
      "mid": 0.16864,
      "spread_bps": 1.18595825426899,
      "selected": true
    }
  ]
}