{
  "run_id": "20260228_06",
  "now_ts": 1772200811,
  "window_start_ts": 1772226000,
  "window_end_ts": 1772229600,
  "regime": "Risk-Off",
  "regime_multiplier": 0.0,
  "counts": {
    "universe": 21,
    "scored": 21,
    "selected": 4,
    "targets_pre_risk": 4,
    "orders_exit": 24,
    "orders_rebalance": 0
  },
  "top_scores": [
    {
      "symbol": "DOT/USDT",
      "score": 1.7743430323988323
    },
    {
      "symbol": "ADA/USDT",
      "score": -0.4944415272531203
    },
    {
      "symbol": "ETC/USDT",
      "score": -0.547842450468683
    },
    {
      "symbol": "BNB/USDT",
      "score": -0.5595060436009727
    },
    {
      "symbol": "LTC/USDT",
      "score": -0.5766475197844194
    },
    {
      "symbol": "UNI/USDT",
      "score": -0.630931984395826
    },
    {
      "symbol": "POL/USDT",
      "score": -0.7870860253124778
    },
    {
      "symbol": "BTC/USDT",
      "score": -0.8639926149327483
    },
    {
      "symbol": "LINK/USDT",
      "score": -0.876075835096708
    },
    {
      "symbol": "NEAR/USDT",
      "score": -0.8780915147962751
    }
  ],
  "targets_pre_risk": {
    "DOT/USDT": 0.0,
    "ADA/USDT": 0.0,
    "ETC/USDT": 0.0,
    "BNB/USDT": 0.0
  },
  "targets_post_risk": {
    "DOT/USDT": 0.0,
    "ADA/USDT": 0.0,
    "ETC/USDT": 0.0,
    "BNB/USDT": 0.0
  },
  "portfolio_debug": {},
  "rebalance_deadband_pct": null,
  "rebalance_skipped_deadband_count": 0,
  "rebalance_skipped_deadband_by_symbol": {},
  "rebalance_drift_by_symbol": {},
  "rebalance_effective_deadband_by_symbol": {},
  "router_decisions": [
    {
      "symbol": "ADA/USDT",
      "action": "skip",
      "reason": "deadband",
      "drift": 0.0,
      "deadband": 0.07,
      "is_new_position": true
    },
    {
      "symbol": "BNB/USDT",
      "action": "skip",
      "reason": "deadband",
      "drift": 0.0,
      "deadband": 0.07,
      "is_new_position": true
    },
    {
      "symbol": "DOT/USDT",
      "action": "skip",
      "reason": "deadband",
      "drift": 0.0,
      "deadband": 0.07,
      "is_new_position": true
    },
    {
      "symbol": "ETC/USDT",
      "action": "skip",
      "reason": "deadband",
      "drift": 0.0,
      "deadband": 0.07,
      "is_new_position": true
    }
  ],
  "rejects": {
    "no_closed_bar": 0,
    "min_notional": 0,
    "spread_gate": 0,
    "dd_throttle": 1,
    "cap_clipped": 0,
    "insufficient_cash": 0,
    "deadband_skip": 4,
    "provider_error": 0,
    "exchange_min_notional": 0
  },
  "budget": {
    "ymd_utc": "20260227",
    "avg_equity_est": 109.01435050955753,
    "turnover_used": 14.981494816849999,
    "turnover_budget_per_day": null,
    "cost_used_usdt": 0.025665170466849997,
    "cost_used_bps": 2.354292838225906,
    "cost_budget_bps_per_day": null,
    "exceeded": false,
    "reason": null,
    "fills_count_today": 5,
    "median_notional_usdt_today": 2.8695,
    "small_trade_ratio_today": 0.0,
    "small_trade_notional_cutoff": 2.5
  },
  "budget_action": {
    "enabled": false
  },
  "universe_config": {
    "enabled": true,
    "use_universe_symbols": true,
    "config_symbols_count": 4,
    "actual_symbols_count": 21,
    "actual_symbols_sample": [
      "BTC/USDT",
      "ETH/USDT",
      "SOL/USDT",
      "BNB/USDT",
      "ADA/USDT",
      "DOT/USDT",
      "AVAX/USDT",
      "POL/USDT",
      "ATOM/USDT",
      "NEAR/USDT"
    ]
  },
  "exit_signals": [
    {
      "symbol": "ETH/USDT",
      "side": "sell",
      "intent": "CLOSE_LONG",
      "reason": "profit_taking_stop_loss_hit_hold",
      "last": 1921.35,
      "stop": null,
      "highest": null,
      "atr": null,
      "atr_mult": null,
      "atr_n": null
    },
    {
      "symbol": "AAVE/USDT",
      "side": "sell",
      "intent": "CLOSE_LONG",
      "reason": "profit_taking_stop_loss_hit_hold",
      "last": 111.77,
      "stop": null,
      "highest": null,
      "atr": null,
      "atr_mult": null,
      "atr_n": null
    },
    {
      "symbol": "SOL/USDT",
      "side": "sell",
      "intent": "CLOSE_LONG",
      "reason": "profit_taking_stop_loss_hit_hold",
      "last": 81.2,
      "stop": null,
      "highest": null,
      "atr": null,
      "atr_mult": null,
      "atr_n": null
    },
    {
      "symbol": "ETC/USDT",
      "side": "sell",
      "intent": "CLOSE_LONG",
      "reason": "profit_taking_stop_loss_hit_hold",
      "last": 8.592,
      "stop": null,
      "highest": null,
      "atr": null,
      "atr_mult": null,
      "atr_n": null
    },
    {
      "symbol": "AVAX/USDT",
      "side": "sell",
      "intent": "CLOSE_LONG",
      "reason": "profit_taking_stop_loss_hit_hold",
      "last": 8.892,
      "stop": null,
      "highest": null,
      "atr": null,
      "atr_mult": null,
      "atr_n": null
    },
    {
      "symbol": "DOGE/USDT",
      "side": "sell",
      "intent": "CLOSE_LONG",
      "reason": "profit_taking_stop_loss_hit_hold",
      "last": 0.0931,
      "stop": null,
      "highest": null,
      "atr": null,
      "atr_mult": null,
      "atr_n": null
    },
    {
      "symbol": "POL/USDT",
      "side": "sell",
      "intent": "CLOSE_LONG",
      "reason": "fixed_stop_loss",
      "last": 0.10813,
      "stop": null,
      "highest": null,
      "atr": null,
      "atr_mult": null,
      "atr_n": null
    },
    {
      "symbol": "BTC/USDT",
      "side": "sell",
      "intent": "CLOSE_LONG",
      "reason": "fixed_stop_loss",
      "last": 65529.4,
      "stop": null,
      "highest": null,
      "atr": null,
      "atr_mult": null,
      "atr_n": null
    },
    {
      "symbol": "UNI/USDT",
      "side": "sell",
      "intent": "CLOSE_LONG",
      "reason": "fixed_stop_loss",
      "last": 3.716,
      "stop": null,
      "highest": null,
      "atr": null,
      "atr_mult": null,
      "atr_n": null
    },
    {
      "symbol": "BNB/USDT",
      "side": "sell",
      "intent": "CLOSE_LONG",
      "reason": "regime_exit",
      "last": 611.2,
      "stop": null,
      "highest": null,
      "atr": null,
      "atr_mult": null,
      "atr_n": null
    },
    {
      "symbol": "LTC/USDT",
      "side": "sell",
      "intent": "CLOSE_LONG",
      "reason": "regime_exit",
      "last": 54.05,
      "stop": null,
      "highest": null,
      "atr": null,
      "atr_mult": null,
      "atr_n": null
    },
    {
      "symbol": "TRX/USDT",
      "side": "sell",
      "intent": "CLOSE_LONG",
      "reason": "regime_exit",
      "last": 0.28283,
      "stop": null,
      "highest": null,
      "atr": null,
      "atr_mult": null,
      "atr_n": null
    },
    {
      "symbol": "XAUT/USDT",
      "side": "sell",
      "intent": "CLOSE_LONG",
      "reason": "regime_exit",
      "last": 0.0,
      "stop": null,
      "highest": null,
      "atr": null,
      "atr_mult": null,
      "atr_n": null
    },
    {
      "symbol": "PROMPT/USDT",
      "side": "sell",
      "intent": "CLOSE_LONG",
      "reason": "regime_exit",
      "last": 0.0,
      "stop": null,
      "highest": null,
      "atr": null,
      "atr_mult": null,
      "atr_n": null
    },
    {
      "symbol": "SPACE/USDT",
      "side": "sell",
      "intent": "CLOSE_LONG",
      "reason": "regime_exit",
      "last": 0.0,
      "stop": null,
      "highest": null,
      "atr": null,
      "atr_mult": null,
      "atr_n": null
    },
    {
      "symbol": "KITE/USDT",
      "side": "sell",
      "intent": "CLOSE_LONG",
      "reason": "regime_exit",
      "last": 0.0,
      "stop": null,
      "highest": null,
      "atr": null,
      "atr_mult": null,
      "atr_n": null
    },
    {
      "symbol": "WLFI/USDT",
      "side": "sell",
      "intent": "CLOSE_LONG",
      "reason": "regime_exit",
      "last": 0.0,
      "stop": null,
      "highest": null,
      "atr": null,
      "atr_mult": null,
      "atr_n": null
    },
    {
      "symbol": "MERL/USDT",
      "side": "sell",
      "intent": "CLOSE_LONG",
      "reason": "regime_exit",
      "last": 0.0,
      "stop": null,
      "highest": null,
      "atr": null,
      "atr_mult": null,
      "atr_n": null
    },
    {
      "symbol": "J/USDT",
      "side": "sell",
      "intent": "CLOSE_LONG",
      "reason": "regime_exit",
      "last": 0.0,
      "stop": null,
      "highest": null,
      "atr": null,
      "atr_mult": null,
      "atr_n": null
    },
    {
      "symbol": "PEPE/USDT",
      "side": "sell",
      "intent": "CLOSE_LONG",
      "reason": "regime_exit",
      "last": 0.0,
      "stop": null,
      "highest": null,
      "atr": null,
      "atr_mult": null,
      "atr_n": null
    },
    {
      "symbol": "DOT/USDT",
      "side": "sell",
      "intent": "CLOSE_LONG",
      "reason": "regime_exit",
      "last": 1.626,
      "stop": null,
      "highest": null,
      "atr": null,
      "atr_mult": null,
      "atr_n": null
    },
    {
      "symbol": "FIL/USDT",
      "side": "sell",
      "intent": "CLOSE_LONG",
      "reason": "regime_exit",
      "last": 0.0,
      "stop": null,
      "highest": null,
      "atr": null,
      "atr_mult": null,
      "atr_n": null
    },
    {
      "symbol": "AGLD/USDT",
      "side": "sell",
      "intent": "CLOSE_LONG",
      "reason": "regime_exit",
      "last": 0.0,
      "stop": null,
      "highest": null,
      "atr": null,
      "atr_mult": null,
      "atr_n": null
    },
    {
      "symbol": "USDG/USDT",
      "side": "sell",
      "intent": "CLOSE_LONG",
      "reason": "regime_exit",
      "last": 0.0,
      "stop": null,
      "highest": null,
      "atr": null,
      "atr_mult": null,
      "atr_n": null
    }
  ],
  "notes": [
    "2026-02-27T22:00:26.310424: Strategy signal audit error: cannot access local variable 'json' where it is no",
    "2026-02-27T22:00:26.317087: DD multiplier: 0.6 (drawdown: 24.13%)",
    "2026-02-27T22:00:26.321024: Profit taking: ETH/USDT stop_loss_hit_hold",
    "2026-02-27T22:00:26.321540: Fixed stop loss: POL/USDT loss -7.1%",
    "2026-02-27T22:00:26.321648: Fixed stop loss: BTC/USDT loss -4.4%",
    "2026-02-27T22:00:26.321665: Profit taking: AAVE/USDT stop_loss_hit_hold",
    "2026-02-27T22:00:26.321694: Profit taking: SOL/USDT stop_loss_hit_hold",
    "2026-02-27T22:00:26.321711: Profit taking: ETC/USDT stop_loss_hit_hold",
    "2026-02-27T22:00:26.321721: Profit taking: AVAX/USDT stop_loss_hit_hold",
    "2026-02-27T22:00:26.321739: Fixed stop loss: UNI/USDT loss -8.0%",
    "2026-02-27T22:00:26.321761: Profit taking: DOGE/USDT stop_loss_hit_hold",
    "2026-02-27T22:00:26.322615: Rank exit: BNB/USDT rank 4, rank_4_exceeds_3",
    "2026-02-27T22:00:26.322679: Rank exit: LTC/USDT rank 5, rank_5_exceeds_3",
    "2026-02-27T22:00:26.322705: Rank exit: TRX/USDT rank 11, rank_11_exceeds_3",
    "2026-02-27T22:00:26.324033: Risk-Off close-only: rebalance buy suppressed (pos_mult_risk_off<=0)",
    "2026-02-27T22:00:26.324201: Dust filter: ETH/USDT qty=0.00000160 value=$0.0031 treated as 0",
    "2026-02-27T22:00:26.324216: Dust filter: POL/USDT qty=0.00754000 value=$0.0008 treated as 0",
    "2026-02-27T22:00:26.324223: Dust filter: BNB/USDT qty=0.00000065 value=$0.0004 treated as 0",
    "2026-02-27T22:00:26.324229: Dust filter: BTC/USDT qty=0.00000000 value=$0.0002 treated as 0",
    "2026-02-27T22:00:26.324239: Dust filter: AAVE/USDT qty=0.00000049 value=$0.0001 treated as 0",
    "2026-02-27T22:00:26.324245: Dust filter: LTC/USDT qty=0.00000083 value=$0.0000 treated as 0",
    "2026-02-27T22:00:26.324251: Dust filter: SOL/USDT qty=0.00000028 value=$0.0000 treated as 0",
    "2026-02-27T22:00:26.324258: Dust filter: ETC/USDT qty=0.00000076 value=$0.0000 treated as 0",
    "2026-02-27T22:00:26.324263: Dust filter: AVAX/USDT qty=0.00000048 value=$0.0000 treated as 0",
    "2026-02-27T22:00:26.324269: Dust filter: UNI/USDT qty=0.00000009 value=$0.0000 treated as 0",
    "2026-02-27T22:00:26.324275: Dust filter: DOT/USDT qty=0.00000020 value=$0.0000 treated as 0",
    "2026-02-27T22:00:26.324281: Dust filter: DOGE/USDT qty=0.00000099 value=$0.0000 treated as 0",
    "2026-02-27T22:00:26.324286: Dust filter: TRX/USDT qty=0.00000004 value=$0.0000 treated as 0",
    "2026-02-27T22:00:26.325129: Banding: ADA/USDT is new position, deadband 0.07→0.070",
    "2026-02-27T22:00:26.325209: Banding: BNB/USDT is new position, deadband 0.07→0.070",
    "2026-02-27T22:00:26.325218: Banding: DOT/USDT is new position, deadband 0.07→0.070",
    "2026-02-27T22:00:26.325225: Banding: ETC/USDT is new position, deadband 0.07→0.070"
  ],
  "regime_details": {
    "method": "EnsembleRegimeEngine",
    "votes": {
      "hmm": {
        "state": "RISK_OFF",
        "confidence": 0.9711909245119885,
        "weight": 0.35,
        "sentiment": -0.971055496715518,
        "raw_state": "TrendingDown",
        "probs": {
          "TrendingUp": 0.00013542779647042531,
          "TrendingDown": 0.9711909245119885,
          "Sideways": 0.028673647591541014
        }
      },
      "funding": {
        "state": "SIDEWAYS",
        "confidence": 0.006,
        "weight": 0.4,
        "sentiment": 0.003,
        "composite": true,
        "details": {
          "large": {
            "avg": 0.05855,
            "count": 2
          },
          "mid": {
            "avg": -0.062975,
            "count": 4
          },
          "small": {
            "avg": -0.03715,
            "count": 4
          }
        }
      },
      "rss": {
        "state": "SIDEWAYS",
        "confidence": 0.6000000000000001,
        "weight": 0.25,
        "sentiment": 0.2,
        "summary": "[RSS情报] 加密货币市场情绪谨慎乐观，机构采用和监管行动带来积极信号，但宏观风险和价格波动引发担忧。"
      }
    },
    "final_score": 0.33991682357919595,
    "hmm_weight": 0.35,
    "funding_weight": 0.4,
    "rss_weight": 0.25
  },
  "strategy_signals": []
}