{
  "run_id": "20260305_141506",
  "now_ts": 1772691306,
  "window_start_ts": null,
  "window_end_ts": null,
  "regime": "Sideways",
  "regime_multiplier": 0.6495978685916141,
  "counts": {
    "universe": 28,
    "scored": 26,
    "selected": 3,
    "targets_pre_risk": 3,
    "orders_exit": 0,
    "orders_rebalance": 0
  },
  "top_scores": [
    {
      "symbol": "IP/USDT",
      "score": 1.0555395381657384
    },
    {
      "symbol": "BCH/USDT",
      "score": 1.048654875884164
    },
    {
      "symbol": "DOGE/USDT",
      "score": 0.2458899393425623
    },
    {
      "symbol": "CC/USDT",
      "score": 0.18531467483556893
    },
    {
      "symbol": "ADA/USDT",
      "score": 0.03935223372458024
    },
    {
      "symbol": "PUMP/USDT",
      "score": 0.03580993880758139
    },
    {
      "symbol": "TRX/USDT",
      "score": 0.01753853116795636
    },
    {
      "symbol": "PHA/USDT",
      "score": -0.001420666714844341
    },
    {
      "symbol": "SUI/USDT",
      "score": -0.011230807177943721
    },
    {
      "symbol": "LTC/USDT",
      "score": -0.01754149587308911
    }
  ],
  "targets_pre_risk": {
    "NEAR/USDT": 0.21352941821051838,
    "UNI/USDT": 0.2204051540927167,
    "BTC/USDT": 0.21566329628837896
  },
  "targets_post_risk": {
    "NEAR/USDT": 0.12811765092631103,
    "UNI/USDT": 0.13224309245563,
    "BTC/USDT": 0.12939797777302736
  },
  "portfolio_debug": {
    "inv_vol_norm": {
      "NEAR/USDT": 0.24486582512387195,
      "UNI/USDT": 0.30020236492260305,
      "BTC/USDT": 0.454931809953525
    },
    "confidence_raw": {
      "NEAR/USDT": 0.41918873086739766,
      "UNI/USDT": 0.35292928459713147,
      "BTC/USDT": 0.22788198453547087
    },
    "score_stats": {
      "min": 1.1336490037348894,
      "max": 1.6821930339556401,
      "std": 0.2309100189003555,
      "count": 3
    },
    "zero_reason_by_symbol": {},
    "weight_pre_clip": {
      "NEAR/USDT": 0.3287101582914198,
      "UNI/USDT": 0.3392947618048296,
      "BTC/USDT": 0.33199507990375055
    }
  },
  "rebalance_deadband_pct": 0.05,
  "rebalance_skipped_deadband_count": 4,
  "rebalance_skipped_deadband_by_symbol": {
    "APT/USDT": 0.0,
    "BARD/USDT": 0.0,
    "BTC/USDT": 0.001200849489228939,
    "NEAR/USDT": 0.0010753763414964868
  },
  "rebalance_drift_by_symbol": {
    "APT/USDT": 0.0,
    "BARD/USDT": 0.0,
    "BTC/USDT": 0.001200849489228939,
    "NEAR/USDT": -0.0010753763414964868,
    "UNI/USDT": 0.05698599849447264
  },
  "rebalance_effective_deadband_by_symbol": {
    "APT/USDT": 0.05,
    "BARD/USDT": 0.05,
    "BTC/USDT": 0.05,
    "NEAR/USDT": 0.05,
    "UNI/USDT": 0.05
  },
  "router_decisions": [
    {
      "symbol": "APT/USDT",
      "action": "skip",
      "reason": "deadband",
      "drift": 0.0,
      "deadband": 0.05,
      "is_new_position": true
    },
    {
      "symbol": "BARD/USDT",
      "action": "skip",
      "reason": "deadband",
      "drift": 0.0,
      "deadband": 0.05,
      "is_new_position": true
    },
    {
      "symbol": "BTC/USDT",
      "action": "skip",
      "reason": "deadband",
      "drift": 0.001200849489228939,
      "deadband": 0.05,
      "is_new_position": false
    },
    {
      "symbol": "NEAR/USDT",
      "action": "skip",
      "reason": "deadband",
      "drift": -0.0010753763414964868,
      "deadband": 0.05,
      "is_new_position": false
    },
    {
      "symbol": "UNI/USDT",
      "action": "skip",
      "reason": "min_notional",
      "notional": 5.292810628917865,
      "min_notional": 9.0
    }
  ],
  "rejects": {
    "no_closed_bar": 0,
    "min_notional": 1,
    "spread_gate": 0,
    "dd_throttle": 1,
    "cap_clipped": 0,
    "insufficient_cash": 0,
    "deadband_skip": 4,
    "provider_error": 0,
    "exchange_min_notional": 0
  },
  "budget": {
    "equity_cap_usdt": null,
    "current_equity_usdt": 132.0579339718657,
    "utilization_pct": null,
    "action_enabled": false
  },
  "budget_action": {
    "enabled": false
  },
  "universe_config": {
    "enabled": true,
    "use_universe_symbols": true,
    "config_symbols_count": 4,
    "actual_symbols_count": 28,
    "actual_symbols_sample": [
      "BTC/USDT",
      "ETH/USDT",
      "OKB/USDT",
      "DOGE/USDT",
      "SOL/USDT",
      "XRP/USDT",
      "SUI/USDT",
      "CC/USDT",
      "HYPE/USDT",
      "LINK/USDT"
    ]
  },
  "exit_signals": [],
  "notes": [
    "2026-03-05T14:15:18.829777: alpha weights overridden by regime=Sideways from reports/alpha_dynamic_weights_by_regime.json",
    "2026-03-05T14:15:18.829992: Multi-strategy: 3 strategies, 33 total signals",
    "2026-03-05T14:15:18.829998:   TrendFollowing: 4 signals (4 buy, 0 sell)",
    "2026-03-05T14:15:18.830000:   MeanReversion: 2 signals (0 buy, 2 sell)",
    "2026-03-05T14:15:18.830002:   Alpha6Factor: 27 signals (18 buy, 9 sell)",
    "2026-03-05T14:15:18.831133: DD multiplier: 0.6 (drawdown: 31.19%)",
    "2026-03-05T14:15:18.831395: Using fused signals for selection: ['ASTER/USDT', 'XPL/USDT', 'TON/USDT', 'BTC/USDT', 'ETH/USDT']",
    "2026-03-05T14:15:18.831475: AutoRisk position cap applied: max_positions=3",
    "2026-03-05T14:15:18.831479: Using fused scores for weighting",
    "2026-03-05T14:15:18.853443: Rank exit source: fused, candidates=26",
    "2026-03-05T14:15:18.853459: Rank exit skipped: NEAR/USDT target_w=0.1281 > eps=0.0010",
    "2026-03-05T14:15:18.853462: Rank exit skipped: BTC/USDT target_w=0.1294 > eps=0.0010",
    "2026-03-05T14:15:18.853465: Rank exit skipped: UNI/USDT target_w=0.1322 > eps=0.0010",
    "2026-03-05T14:15:18.853721: Banding: APT/USDT is new position, deadband 0.05→0.050",
    "2026-03-05T14:15:18.853735: Banding: BARD/USDT is new position, deadband 0.05→0.050"
  ],
  "regime_details": {
    "method": "EnsembleRegimeEngine",
    "votes": {
      "hmm": {
        "state": "SIDEWAYS",
        "confidence": 0.9726422161553903,
        "weight": 0.35,
        "sentiment": 0.012264591955002384,
        "raw_state": "Sideways",
        "probs": {
          "Sideways": 0.9726422161553903,
          "TrendingUp": 0.0198111878998062,
          "TrendingDown": 0.007546595944803815
        }
      },
      "funding": {
        "state": "SIDEWAYS",
        "confidence": 0.0614,
        "weight": 0.4,
        "sentiment": 0.0307,
        "composite": true,
        "details": {
          "large": {
            "avg": 0.06945,
            "count": 2
          },
          "mid": {
            "avg": -0.024825,
            "count": 4
          },
          "small": {
            "avg": 0.017325,
            "count": 4
          }
        }
      },
      "rss": {
        "state": "TRENDING",
        "confidence": 0.9000000000000001,
        "weight": 0.25,
        "sentiment": 0.4,
        "summary": "[RSS情报] 加密货币市场情绪整体偏积极，机构合作和监管进展带来乐观预期，但技术面显示短期波动风险，市场处于中性偏吸筹阶段。"
      },
      "alerts": [
        "regime_stuck_sideways"
      ],
      "monitor": {
        "enabled": true,
        "db_path": "/home/admin/clawd/v5-trading-bot/reports/regime_history.db",
        "sideways_prob_warn_threshold": 0.8,
        "sideways_consecutive_warn": 10
      }
    },
    "final_score": 0.3649847756543866,
    "hmm_weight": 0.35,
    "funding_weight": 0.4,
    "rss_weight": 0.25
  },
  "strategy_signals": [
    {
      "strategy": "TrendFollowing",
      "type": "trend",
      "allocation": 0.2,
      "total_signals": 4,
      "buy_signals": 4,
      "sell_signals": 0,
      "signals": [
        {
          "symbol": "OKB/USDT",
          "side": "buy",
          "score": 0.7201291969910487,
          "confidence": 0.7761033575928391,
          "metadata": {
            "ma_fast": 82.457,
            "ma_slow": 78.409,
            "adx": 36.006459849552435
          }
        },
        {
          "symbol": "ASTER/USDT",
          "side": "buy",
          "score": 0.651637362426227,
          "confidence": 0.7213098899409818,
          "metadata": {
            "ma_fast": 0.7254050000000001,
            "ma_slow": 0.710275,
            "adx": 32.58186812131135
          }
        },
        {
          "symbol": "XPL/USDT",
          "side": "buy",
          "score": 0.8856561933941423,
          "confidence": 0.9085249547153138,
          "metadata": {
            "ma_fast": 0.114034,
            "ma_slow": 0.11337966666666667,
            "adx": 44.28280966970711
          }
        },
        {
          "symbol": "TON/USDT",
          "side": "buy",
          "score": 0.9230890999671054,
          "confidence": 0.9384712799736843,
          "metadata": {
            "ma_fast": 1.33395,
            "ma_slow": 1.2825166666666667,
            "adx": 46.15445499835527
          }
        }
      ]
    },
    {
      "strategy": "MeanReversion",
      "type": "mean_reversion",
      "allocation": 0.25,
      "total_signals": 2,
      "buy_signals": 0,
      "sell_signals": 2,
      "signals": [
        {
          "symbol": "OKB/USDT",
          "side": "sell",
          "score": 0.3502410396143369,
          "confidence": 0.4152169356529032,
          "metadata": {
            "rsi": 81.80674910920143,
            "deviation": 0.3105012309446137,
            "bb_upper": 104.65517925203012
          }
        },
        {
          "symbol": "TON/USDT",
          "side": "sell",
          "score": 0.4105409153952862,
          "confidence": 0.4694868238557576,
          "metadata": {
            "rsi": 83.49514563106801,
            "deviation": 0.039019453502754924,
            "bb_upper": 1.3863190346433294
          }
        }
      ]
    },
    {
      "strategy": "Alpha6Factor",
      "type": "alpha_6factor",
      "allocation": 0.55,
      "total_signals": 27,
      "buy_signals": 18,
      "sell_signals": 9,
      "signals": [
        {
          "symbol": "BTC/USDT",
          "side": "buy",
          "score": 1.1336490037348894,
          "confidence": 1.0,
          "metadata": {
            "raw_factors": {
              "f1_mom_5d": 0.12009173760084892,
              "f2_mom_20d": 0.07314056547733387,
              "f3_vol_adj_ret": 10.968986958686557,
              "f4_volume_expansion": 0.04587597032702506,
              "f5_rsi_trend_confirm": -0.034670494196838604,
              "f6_sentiment": 0.0839
            },
            "z_factors": {
              "f1_mom_5d": 1.200917376008489,
              "f2_mom_20d": 0.3657028273866693,
              "f3_vol_adj_ret": 5.4844934793432785,
              "f4_volume_expansion": 0.09175194065405012,
              "f5_rsi_trend_confirm": -0.034670494196838604,
              "f6_sentiment": 0.0839
            },
            "final_score": 1.0235183047396974,
            "cross_section_mean": -0.11013069899519203,
            "relative_score": 1.1336490037348894
          }
        },
        {
          "symbol": "ETH/USDT",
          "side": "buy",
          "score": 0.9394922367994731,
          "confidence": 0.9394922367994731,
          "metadata": {
            "raw_factors": {
              "f1_mom_5d": 0.11786671722837563,
              "f2_mom_20d": 0.08332440116169272,
              "f3_vol_adj_ret": 9.933552725347111,
              "f4_volume_expansion": 0.21003371144050131,
              "f5_rsi_trend_confirm": -0.03147596767333056,
              "f6_sentiment": 0.055
            },
            "z_factors": {
              "f1_mom_5d": 1.1786671722837563,
              "f2_mom_20d": 0.4166220058084636,
              "f3_vol_adj_ret": 4.9667763626735555,
              "f4_volume_expansion": 0.42006742288100263,
              "f5_rsi_trend_confirm": -0.03147596767333056,
              "f6_sentiment": 0.055
            },
            "final_score": 0.8293615378042811,
            "cross_section_mean": -0.11013069899519203,
            "relative_score": 0.9394922367994731
          }
        },
        {
          "symbol": "OKB/USDT",
          "side": "sell",
          "score": 5.719867836357349,
          "confidence": 1.0,
          "metadata": {
            "raw_factors": {
              "f1_mom_5d": 0.44813722862503347,
              "f2_mom_20d": 0.3640494824539258,
              "f3_vol_adj_ret": 14.147057041833593,
              "f4_volume_expansion": 20.608061621441276,
              "f5_rsi_trend_confirm": 0.6361349821840286,
              "f6_sentiment": 0.6
            },
            "z_factors": {
              "f1_mom_5d": 4.481372286250334,
              "f2_mom_20d": 1.820247412269629,
              "f3_vol_adj_ret": 7.073528520916796,
              "f4_volume_expansion": 41.21612324288255,
              "f5_rsi_trend_confirm": 0.6361349821840286,
              "f6_sentiment": 0.6
            },
            "final_score": -5.829998535352542,
            "cross_section_mean": -0.11013069899519203,
            "relative_score": -5.719867836357349
          }
        },
        {
          "symbol": "DOGE/USDT",
          "side": "sell",
          "score": 0.7626545280420032,
          "confidence": 0.7626545280420032,
          "metadata": {
            "raw_factors": {
              "f1_mom_5d": 0.05034148490857022,
              "f2_mom_20d": -0.045832082457720406,
              "f3_vol_adj_ret": -5.1504228978190705,
              "f4_volume_expansion": 0.8001049017827275,
              "f5_rsi_trend_confirm": -0.2798395185556673,
              "f6_sentiment": 0.1
            },
            "z_factors": {
              "f1_mom_5d": 0.5034148490857021,
              "f2_mom_20d": -0.229160412288602,
              "f3_vol_adj_ret": -2.5752114489095352,
              "f4_volume_expansion": 1.600209803565455,
              "f5_rsi_trend_confirm": -0.2798395185556673,
              "f6_sentiment": 0.1
            },
            "final_score": -0.8727852270371952,
            "cross_section_mean": -0.11013069899519203,
            "relative_score": -0.7626545280420032
          }
        },
        {
          "symbol": "SOL/USDT",
          "side": "buy",
          "score": 0.8016526376792252,
          "confidence": 0.8016526376792252,
          "metadata": {
            "raw_factors": {
              "f1_mom_5d": 0.12493821057834897,
              "f2_mom_20d": 0.0791938352104328,
              "f3_vol_adj_ret": 8.480437223580841,
              "f4_volume_expansion": -0.030454075231676536,
              "f5_rsi_trend_confirm": 0.031367628607277424,
              "f6_sentiment": -0.0391
            },
            "z_factors": {
              "f1_mom_5d": 1.2493821057834897,
              "f2_mom_20d": 0.395969176052164,
              "f3_vol_adj_ret": 4.240218611790421,
              "f4_volume_expansion": -0.06090815046335307,
              "f5_rsi_trend_confirm": 0.031367628607277424,
              "f6_sentiment": -0.0391
            },
            "final_score": 0.6915219386840332,
            "cross_section_mean": -0.11013069899519203,
            "relative_score": 0.8016526376792252
          }
        }
      ]
    }
  ]
}